IP2Location/__init__.py
IP2Location/country.py
IP2Location/database.py
IP2Location/iptools.py
IP2Location/region.py
IP2Location/webservice.py
IP2Location-8.10.3.dist-info/AUTHORS
IP2Location-8.10.3.dist-info/LICENSE.TXT
IP2Location-8.10.3.dist-info/METADATA
IP2Location-8.10.3.dist-info/WHEEL
IP2Location-8.10.3.dist-info/top_level.txt
IP2Location-8.10.3.dist-info/RECORD
