Metadata-Version: 2.1
Name: IP2Location
Version: 8.10.3
Summary: This is an IP geolocation library that enables the user to find the country, region, city, latitude and longitude, ZIP code, time zone, ISP, domain name, area code, weather info, mobile info, elevation, usage type, address type and IAB category from an IP address. It supports both IPv4 and IPv6 lookup.
Home-page: https://github.com/chrislim2888/ip2location-python
Author: IP2Location
Author-email: support@ip2location.com
Classifier: Development Status :: 5 - Production/Stable
Classifier: Intended Audience :: Developers
Classifier: Topic :: Software Development :: Libraries :: Python Modules
Classifier: Programming Language :: Python :: 3.5
Classifier: Programming Language :: Python :: 3.6
Classifier: Programming Language :: Python :: 3.7
Classifier: Programming Language :: Python :: 3.8
Classifier: Programming Language :: Python :: 3.9
Classifier: Programming Language :: Python :: 3.10
Classifier: Programming Language :: Python :: 3.11
Classifier: Programming Language :: Python :: 3.12
Classifier: License :: OSI Approved :: MIT License
Classifier: Operating System :: OS Independent
License-File: LICENSE.TXT
License-File: AUTHORS
